paginator/__init__.py
paginator/objects.py
paginator/paginator.py
pycord_paging-1.0.0.dist-info/LICENSE
pycord_paging-1.0.0.dist-info/METADATA
pycord_paging-1.0.0.dist-info/WHEEL
pycord_paging-1.0.0.dist-info/top_level.txt
pycord_paging-1.0.0.dist-info/RECORD
