Metadata-Version: 2.1
Name: pycord-paging
Version: 1.0.0
Summary: Pycord paginator for messages and embeds with reactions or buttons.
Home-page: https://github.com/Tommodev-06/pycord-paging
Author: Tommodev
License: MIT
Project-URL: Source, https://github.com/Tommodev-06/pycord-paging
Project-URL: Documentation, https://tommodev.gitbook.io/pycord-paging/
Keywords: pycord paginator pycord-paginator
Platform: UNKNOWN
Classifier: Programming Language :: Python :: 3
Classifier: License :: OSI Approved :: MIT License
Requires-Python: >=3.6
License-File: LICENSE
Requires-Dist: aiohttp
Requires-Dist: py-cord (==2.0.0b4)
Requires-Dist: asyncio
